instant_crud/__init__.py
instant_crud/config/__init__.py
instant_crud/config/settings.py
instant_crud/config/examples/pagination_cursor.json
instant_crud/config/examples/pagination_custom.json
instant_crud/config/examples/pagination_offset.json
instant_crud/config/examples/pagination_page.json
instant_crud/core/__init__.py
instant_crud/core/decorators.py
instant_crud/core/factory.py
instant_crud/core/strings.py
instant_crud/repositories/__init__.py
instant_crud/repositories/base_repository.py
instant_crud/response/__init__.py
instant_crud/response/pagination.py
instant_crud/routers/__init__.py
instant_crud/routers/crud_router.py
instant_crud/services/__init__.py
instant_crud/services/base_service.py
instant_crud/utils/__init__.py
instant_crud/utils/exceptions.py
instant_crud-0.1.1.dist-info/METADATA
instant_crud-0.1.1.dist-info/WHEEL
instant_crud-0.1.1.dist-info/RECORD
