Metadata-Version: 2.4
Name: instant-crud
Version: 0.1.1
Summary: Generate REST APIs instantly from SQLModel definitions
Project-URL: Homepage, https://github.com/yourusername/instant-crud
Project-URL: Repository, https://github.com/yourusername/instant-crud
Project-URL: Documentation, https://instant-crud.readthedocs.io
Project-URL: Issues, https://github.com/yourusername/instant-crud/issues
Author-email: Massimo Ghiani <m.ghiani@gmail.com>
License: MIT
Keywords: code-generation,crud,database,fastapi,orm,rest-api,sqlmodel
Classifier: Development Status :: 3 - Alpha
Classifier: Framework :: FastAPI
Classifier: Framework :: Pydantic
Classifier: Intended Audience :: Developers
Classifier: License :: OSI Approved :: MIT License
Classifier: Programming Language :: Python :: 3.12
Classifier: Topic :: Database
Classifier: Topic :: Internet :: WWW/HTTP :: HTTP Servers
Classifier: Topic :: Software Development :: Libraries :: Python Modules
Requires-Python: >=3.12
Requires-Dist: fastapi>=0.115.8
Requires-Dist: jinja2>=3.1.6
Requires-Dist: pydantic-settings>=2.7.1
Requires-Dist: pydantic>=2.0.0
Requires-Dist: sqlmodel>=0.0.22
Provides-Extra: all
Requires-Dist: black>=24.0.0; extra == 'all'
Requires-Dist: duckdb>=1.2.0; extra == 'all'
Requires-Dist: httpx>=0.28.1; extra == 'all'
Requires-Dist: jinja2>=3.1.6; extra == 'all'
Requires-Dist: pandas>=2.2.3; extra == 'all'
Requires-Dist: passlib>=1.7.4; extra == 'all'
Requires-Dist: pyarrow>=19.0.1; extra == 'all'
Requires-Dist: pytest-asyncio>=0.24.0; extra == 'all'
Requires-Dist: pytest-cov>=4.0.0; extra == 'all'
Requires-Dist: pytest>=8.0.0; extra == 'all'
Requires-Dist: python-jose>=3.4.0; extra == 'all'
Requires-Dist: ruff>=0.1.0; extra == 'all'
Requires-Dist: uvicorn>=0.30.0; extra == 'all'
Requires-Dist: weasyprint>=64.1; extra == 'all'
Requires-Dist: xlsxwriter>=3.2.2; extra == 'all'
Provides-Extra: auth
Requires-Dist: passlib>=1.7.4; extra == 'auth'
Requires-Dist: python-jose>=3.4.0; extra == 'auth'
Provides-Extra: dev
Requires-Dist: black>=24.0.0; extra == 'dev'
Requires-Dist: httpx>=0.28.1; extra == 'dev'
Requires-Dist: pytest-asyncio>=0.24.0; extra == 'dev'
Requires-Dist: pytest-cov>=4.0.0; extra == 'dev'
Requires-Dist: pytest>=8.0.0; extra == 'dev'
Requires-Dist: ruff>=0.1.0; extra == 'dev'
Requires-Dist: uvicorn>=0.30.0; extra == 'dev'
Provides-Extra: export
Requires-Dist: duckdb>=1.2.0; extra == 'export'
Requires-Dist: jinja2>=3.1.6; extra == 'export'
Requires-Dist: pandas>=2.2.3; extra == 'export'
Requires-Dist: pyarrow>=19.0.1; extra == 'export'
Requires-Dist: weasyprint>=64.1; extra == 'export'
Requires-Dist: xlsxwriter>=3.2.2; extra == 'export'
Provides-Extra: full
Requires-Dist: duckdb>=1.2.0; extra == 'full'
Requires-Dist: jinja2>=3.1.6; extra == 'full'
Requires-Dist: pandas>=2.2.3; extra == 'full'
Requires-Dist: passlib>=1.7.4; extra == 'full'
Requires-Dist: pyarrow>=19.0.1; extra == 'full'
Requires-Dist: python-jose>=3.4.0; extra == 'full'
Requires-Dist: weasyprint>=64.1; extra == 'full'
Requires-Dist: xlsxwriter>=3.2.2; extra == 'full'
